dbnomics_json_errors/__init__.py
dbnomics_json_errors/errors.py
dbnomics_json_errors-0.2.1.dist-info/METADATA
dbnomics_json_errors-0.2.1.dist-info/WHEEL
dbnomics_json_errors-0.2.1.dist-info/top_level.txt
dbnomics_json_errors-0.2.1.dist-info/RECORD
